nonebot_plugin_imageutils/__init__.py
nonebot_plugin_imageutils/build_image.py
nonebot_plugin_imageutils/config.py
nonebot_plugin_imageutils/fonts.py
nonebot_plugin_imageutils/gradient.py
nonebot_plugin_imageutils/text2image.py
nonebot_plugin_imageutils/types.py
nonebot_plugin_imageutils-0.1.17.dist-info/METADATA
nonebot_plugin_imageutils-0.1.17.dist-info/WHEEL
nonebot_plugin_imageutils-0.1.17.dist-info/LICENSE
nonebot_plugin_imageutils-0.1.17.dist-info/RECORD
