Metadata-Version: 2.1
Name: nonebot-plugin-imageutils
Version: 0.1.17
Summary: Nonebot2 PIL工具插件
Home-page: https://github.com/noneplugin/nonebot-plugin-imageutils
License: MIT
Author: meetwq
Author-email: meetwq@gmail.com
Requires-Python: >=3.8,<4.0
Classifier: License :: OSI Approved :: MIT License
Classifier: Programming Language :: Python :: 3
Classifier: Programming Language :: Python :: 3.8
Classifier: Programming Language :: Python :: 3.9
Classifier: Programming Language :: Python :: 3.10
Classifier: Programming Language :: Python :: 3.11
Requires-Dist: Pillow (>=9.0.0,<10.0.0)
Requires-Dist: bbcode (>=1.1.0,<2.0.0)
Requires-Dist: fonttools (>=4.0.0,<5.0.0)
Requires-Dist: httpx (>=0.19.0)
Requires-Dist: loguru (>=0.6.0,<0.7.0)
Requires-Dist: matplotlib (>=3.0.0,<4.0.0)
Requires-Dist: nonebot2[fastapi] (>=2.0.0-rc.1,<3.0.0)
Requires-Dist: numpy (>=1.20.0,<2.0.0)
Requires-Dist: opencv-python-headless (>=4.0.0,<5.0.0)
Project-URL: Repository, https://github.com/noneplugin/nonebot-plugin-imageutils
